recovar/__init__.py
recovar/bibtex.py
recovar/constants.py
recovar/icon.png
recovar/protocols.conf
recovar/convert/__init__.py
recovar/convert/convert.py
recovar/convert/convert_zs.py
recovar/protocols/__init__.py
recovar/protocols/protocol_analyze.py
recovar/protocols/protocol_pipeline.py
recovar/tests/__init__.py
recovar/viewers/__init__.py
recovar/viewers/viewer_pipeline.py
scipion_em_recovar-3.1.1.dist-info/LICENSE
scipion_em_recovar-3.1.1.dist-info/METADATA
scipion_em_recovar-3.1.1.dist-info/WHEEL
scipion_em_recovar-3.1.1.dist-info/entry_points.txt
scipion_em_recovar-3.1.1.dist-info/top_level.txt
scipion_em_recovar-3.1.1.dist-info/RECORD
