Metadata-Version: 2.1
Name: scipion-em-recovar
Version: 3.1.1
Summary: Plugin to use RECOVAR within the Scipion framework
Author-email: Scipion Team <scipion@cnb.csic.es>
License: GNU General Public License v3 (GPLv3)
Project-URL: Homepage, https://github.com/scipion-em/scipion-em-recovar
Project-URL: Issues, https://github.com/scipion-em/scipion-em-recovar/issues
Keywords: scipion,cryoem,flexibility,heterogeneity,imageprocessing,scipion-3.0
Classifier: Development Status :: 4 - Beta
Classifier: License :: OSI Approved :: GNU General Public License v3 (GPLv3)
Classifier: Programming Language :: Python :: 3
Requires-Python: >=3.8
License-File: LICENSE
